README.md
setup.py
python_qbo.egg-info/PKG-INFO
python_qbo.egg-info/SOURCES.txt
python_qbo.egg-info/dependency_links.txt
python_qbo.egg-info/requires.txt
python_qbo.egg-info/top_level.txt
qbo/__init__.py
qbo/qbo.py
qbo/utils.py
test/test_qbo.py
test/test_utils.py