Metadata-Version: 2.1
Name: python-qbo
Version: 0.3.0
Summary: UNKNOWN
Home-page: https://github.com/sebrut/python-qbo
Author: Sebastian Rutofski
Author-email: kontakt@sebastian-rutofski.de
License: MIT
Platform: UNKNOWN
Classifier: Programming Language :: Python :: 3
Classifier: License :: OSI Approved :: MIT License
Classifier: Operating System :: OS Independent
